satyr_play/__init__.py
satyr_play-0.0.1.dist-info/LICENSE
satyr_play-0.0.1.dist-info/METADATA
satyr_play-0.0.1.dist-info/WHEEL
satyr_play-0.0.1.dist-info/top_level.txt
satyr_play-0.0.1.dist-info/RECORD
